LICENSE
MANIFEST.in
README.rst
requirements.txt
setup.py
EasyEuler/__init__.py
EasyEuler/cli.py
EasyEuler/config.json
EasyEuler/data.py
EasyEuler/paths.py
EasyEuler/types.py
EasyEuler.egg-info/PKG-INFO
EasyEuler.egg-info/SOURCES.txt
EasyEuler.egg-info/dependency_links.txt
EasyEuler.egg-info/entry_points.txt
EasyEuler.egg-info/not-zip-safe
EasyEuler.egg-info/requires.txt
EasyEuler.egg-info/top_level.txt
EasyEuler/commands/__init__.py
EasyEuler/commands/create.py
EasyEuler/commands/generate_resources.py
EasyEuler/commands/list.py
EasyEuler/commands/show.py
EasyEuler/commands/verify.py
EasyEuler/data/problems.json
EasyEuler/data/resources/202_laserbeam.gif
EasyEuler/data/resources/208_robotwalk.gif
EasyEuler/data/resources/215_crackfree.gif
EasyEuler/data/resources/220.gif
EasyEuler/data/resources/226_formula.gif
EasyEuler/data/resources/226_scoop2.gif
EasyEuler/data/resources/228.png
EasyEuler/data/resources/237.gif
EasyEuler/data/resources/244_example.gif
EasyEuler/data/resources/244_start.gif
EasyEuler/data/resources/244_target.gif
EasyEuler/data/resources/246_anim.gif
EasyEuler/data/resources/246_ellipse.gif
EasyEuler/data/resources/247_hypersquares.gif
EasyEuler/data/resources/251_cardano.gif
EasyEuler/data/resources/252_convexhole.gif
EasyEuler/data/resources/255_Example.gif
EasyEuler/data/resources/255_Heron.gif
EasyEuler/data/resources/256_tatami3.gif
EasyEuler/data/resources/257_bisector.gif
EasyEuler/data/resources/262_formula1.gif
EasyEuler/data/resources/264_TriangleCentres.gif
EasyEuler/data/resources/265_BinaryCircles.gif
EasyEuler/data/resources/270_CutSquare.gif
EasyEuler/data/resources/275_sculptures2.gif
EasyEuler/data/resources/281_pizza.gif
EasyEuler/data/resources/282_formula.gif
EasyEuler/data/resources/287_quadtree.gif
EasyEuler/data/resources/289_euler.gif
EasyEuler/data/resources/291_formula.gif
EasyEuler/data/resources/295_lenticular.gif
EasyEuler/data/resources/299_ThreeSimTri.gif
EasyEuler/data/resources/300_protein.gif
EasyEuler/data/resources/306_pstrip.gif
EasyEuler/data/resources/309_ladders.gif
EasyEuler/data/resources/311_biclinic.gif
EasyEuler/data/resources/312_sierpinsky8t.gif
EasyEuler/data/resources/312_sierpinskyAt.gif
