Metadata-Version: 1.1
Name: EasyEuler
Version: 1.2.0
Summary: A command line tool for Project Euler
Home-page: https://github.com/Encrylize/EasyEuler
Author: Encrylize
Author-email: encrylize@gmail.com
License: MIT
Keywords: EasyEuler,ProjectEuler,euler,Project-Euler
Platform: UNKNOWN
Classifier: License :: OSI Approved :: MIT License
Classifier: Topic :: Utilities
Classifier: Environment :: Console
Classifier: Intended Audience :: Developers
Classifier: Development Status :: 4 - Beta
Classifier: Programming Language :: Python :: 3.5
Classifier: Operating System :: Microsoft :: Windows
Classifier: Operating System :: Unix
Classifier: Natural Language :: English
